{"todo.md":"1328a51a","blog_css_sass的常用功能用法.md":"e82f0764","blog_css_img标签底部白边处理.md":"95239beb","blog_css_使用filter属性实现高斯模糊.md":"cd04c7e0","blog_css_样式统一.md":"bf7c2553","blog_es6_plus_es6与commonjs模块导入导出的区别.md":"dee3e363","blog_es6_plus_promise.md":"71678ec8","blog_es6_plus_readme.md":"6d229b45","blog_es6_plus_数组方法.md":"6f825b3b","blog_git相关_readme.md":"5bf8c106","blog_git相关_git submodules开发模式.md":"15335620","blog_git相关_github pages配置.md":"a6e93fda","blog_git相关_git报错的解决方案.md":"eff7c735","blog_git相关_git提交日志规范.md":"627c6dca","blog_h5开发_h5定位终极解决方案.md":"2d10c111","blog_h5开发_readme.md":"e1bf7123","blog_js_readme.md":"b240b267","blog_javascript_javascript中的this、call、apply.md":"481e772c","blog_javascript_readme.md":"c3ad54b0","blog_javascript_数组方法.md":"8c17209f","blog_javascript_构造函数.md":"6c189110","blog_linux_linux常用命令大全.md":"43a22a99","blog_react相关_react diff算法.md":"9dc7c545","blog_react相关_react hooks.md":"235db5f6","blog_react相关_react-router使用及其原理.md":"7df82abf","blog_react相关_react原理解析.md":"9f5df037","blog_react相关_react最佳实践.md":"55dc73d7","blog_react相关_react生命周期概述.md":"218d8d95","blog_react相关_react组件设计原则.md":"741aaf94","blog_react相关_react组件跨层级通信之context.md":"7129727c","blog_react相关_react高阶组件-hoc.md":"6d8fb1e5","blog_react相关_redux使用及其原理.md":"c9918c14","blog_react相关_使用react portal实现一个通知栏组件.md":"dfe9d653","blog_react相关_使用react-app-rewired覆盖cra配置.md":"21e412cc","blog_taro_taro踩坑指南.md":"d467d642","blog_vscode_vscode快捷键.md":"4a125406","blog_vscode_vscode插件开发.md":"c1eb3d5f","blog_vscode_vscode扩展.md":"72a15d1f","blog_vscode_使用setting sync同步vscode设置.md":"47313a32","blog_vscode_工作区相关.md":"30816c87","blog_vue_vue的生命周期.md":"e1f611ed","blog_app交互_app webview中富文本超链接点击无反应的解决方案.md":"0db50b24","blog_brainstorming_e-commerce-pr-system.md":"ff70beb6","blog_construct_搭建基于vite的react技术栈应用.md":"ab953466","blog_guide.md":"3f8302e7","blog_markdown相关_readme.md":"7e90669e","blog_nestjs_build-api-docs.md":"fb29c223","blog_nestjs_init-project.md":"d4cbd032","blog_npm相关_corepack实践.md":"cff32df7","blog_npm相关_npm发布node包指北.md":"d5835e47","blog_npm相关_npm常用命令.md":"6cc07c86","blog_plan_coming-soon.md":"ab073950","blog_tools_chrome插件.md":"b1f2d757","blog_tools_常用网站.md":"5b6f3d44","blog_其他_http请求状态码.md":"e731f30a","blog_其他_mac操作指南.md":"e1fd1250","blog_其他_plan.md":"fd1069a7","blog_其他_ssh多配置共存.md":"f7457b37","blog_其他_使用vim编辑和保存文件.md":"1b3b5325","blog_其他_全栈图谱.md":"3b9dd77c","blog_其他_前端代码审查清单.md":"e87c9a19","blog_其他_前端客服功能的设计.md":"8193931e","blog_其他_前端开发环境搭建.md":"f8bd98de","blog_其他_前端技术栈.md":"0dca1f07","blog_其他_如何写出优雅的代码.md":"05915dce","blog_其他_如何在同一台服务器上部署前后端分离项目.md":"1aeba8cb","blog_其他_工具箱.md":"b035de8d","blog_其他_常用linux命令.md":"f8b2770b","blog_其他_常用手机软件.md":"ab6dad98","blog_其他_移动端兼容性问题解决方案.md":"2cd083a3","blog_其他_面试经验.md":"7dee7ac2","blog_前端工程化_gitlab_tag创建规范.md":"c0fa3bb8","blog_前端工程化_gitlab_协作开发流程.md":"61f82c89","blog_前端工程化_lerna管理monorepo实践.md":"b5b3b374","blog_前端工程化_readme.md":"15fc6cde","blog_前端工程化_package.json配置详解.md":"c6a1d1ee","blog_前端工程化_taro多端项目搭建.md":"a207646e","blog_前端工程化_taro小程序mobx项目搭建.md":"a1b20471","blog_前端工程化_yarn-workspace实践.md":"a52e21ce","blog_前端工程化_使用github actions自动化构建项目.md":"6482ba71","blog_前端工程化_使用rollup构建javascript库.md":"7ef2f89b","blog_前端工程化_使用webpack搭建移动端单页应用.md":"419ef465","blog_前端工程化_前后端分离.md":"bbb2da8d","blog_前端工程化_前端项目脚手架搭建.md":"9c156237","blog_前端工程化_无界微前端实践.md":"73b1d86b","blog_前端工程化_框架搭建的难题.md":"e9fccaa1","blog_前端工程化_项目文档的编写.md":"475c1b59","blog_前端资源集合_readme.md":"b49d11ff","blog_博客部署_docsify和vercel搭建博客.md":"d79a26c6","blog_博客部署_vuepress部署博客.md":"d296dd18","blog_小程序_小程序按需构建及分包思路.md":"78f74cdc","blog_小程序_微信小程序获取经纬度不准确的解决方案.md":"1502ce0d","blog_开源_从零开始给开源项目做贡献.md":"0e08f955","blog_总结与展望_2019年度总结.md":"36e4d2dd","blog_未分类_2020.03.15.md":"d3240db6","blog_流程_一次血与泪的教训.m.md":"caaa45ae","blog_测试用例_购物车通用测试用例.md":"ab57aaf3","blog_点滴_2019.11.19.md":"aade82ba","blog_点滴_2020.01.14.md":"9502b0c6","blog_点滴_2021年中总结.md":"291d9b25","blog_点滴_2021年终总结.md":"837d66e4","blog_用户交互_readme.md":"10065c46","blog_编码规范_taro项目规范.md":"9a495188","blog_编码规范_commitlint钩子配置.md":"5a65336e","blog_编码规范_editorconfig配置.md":"305deff8","blog_编码规范_关于代码规范推行的思考.md":"a965e4cc","blog_编码规范_规范工具收集.md":"918700f2","blog_联调的经验_与后端联调.md":"687b3067","blog_记录_blog-tutorial.md":"4c2f8a5e","index.md":"9414589f","tools_gcm.md":"80c05e4e","tools_mpp.md":"8a74c842","tools_tools.md":"b33ec3dc"}
